mcp_server_creator/__init__.py
mcp_server_creator/mcp_server_creator.py
mcp_server_creator-0.1.3.dist-info/METADATA
mcp_server_creator-0.1.3.dist-info/WHEEL
mcp_server_creator-0.1.3.dist-info/entry_points.txt
mcp_server_creator-0.1.3.dist-info/licenses/LICENSE
mcp_server_creator-0.1.3.dist-info/RECORD
