Metadata-Version: 2.4
Name: mcp-server-creator
Version: 0.1.3
Summary: A powerful Model Context Protocol (MCP) server that creates other MCP servers! This meta-server provides tools for dynamically generating FastMCP server configurations and Python code.
Project-URL: Homepage, https://github.com/GongRzhe/MCP-Server-Creator
Project-URL: Bug Tracker, https://github.com/GongRzhe/MCP-Server-Creator/issues
Author-email: GongRzhe <gongrzhe@gmail.com>
License: MIT License
License-File: LICENSE
Keywords: code-generation,developer-tools,fastmcp,mcp,server-generator
Classifier: Development Status :: 4 - Beta
Classifier: Environment :: Console
Classifier: Intended Audience :: Developers
Classifier: License :: OSI Approved :: MIT License
Classifier: Programming Language :: Python :: 3
Classifier: Programming Language :: Python :: 3.8
Classifier: Programming Language :: Python :: 3.9
Classifier: Programming Language :: Python :: 3.10
Classifier: Programming Language :: Python :: 3.11
Classifier: Programming Language :: Python :: 3.12
Classifier: Topic :: Software Development :: Code Generators
Classifier: Topic :: Software Development :: Libraries :: Python Modules
Classifier: Topic :: Utilities
Requires-Python: >=3.8
Requires-Dist: fastmcp>=2.8.1
